importmonkey/__init__.py
importmonkey-2.1.1.dist-info/METADATA
importmonkey-2.1.1.dist-info/WHEEL
importmonkey-2.1.1.dist-info/top_level.txt
importmonkey-2.1.1.dist-info/RECORD
