Metadata-Version: 2.1
Name: importmonkey
Version: 2.1.1
Summary: Utility for adding new import paths.
Author: Markus Hirsimäki
License: The Unlicense
Project-URL: homepage, https://github.com/hirsimaki-markus/importmonkey
Project-URL: issues, https://github.com/hirsimaki-markus/importmonkey/issues
Project-URL: license, https://choosealicense.com/licenses/unlicense/
Classifier: Development Status :: 5 - Production/Stable
Classifier: Programming Language :: Python
Classifier: License :: OSI Approved :: The Unlicense (Unlicense)
Classifier: License :: Public Domain
Classifier: Operating System :: OS Independent
Provides-Extra: dev
Requires-Dist: build ; extra == 'dev'
Requires-Dist: twine ; extra == 'dev'
Requires-Dist: ruff ; extra == 'dev'
